MANIFEST.in
README.rst
setup.cfg
setup.py
subseek/__init__.py
subseek/__main__.py
subseek/constants.py
subseek/models.py
subseek/options.py
subseek/utils.py
subseek.egg-info/PKG-INFO
subseek.egg-info/SOURCES.txt
subseek.egg-info/dependency_links.txt
subseek.egg-info/requires.txt
subseek.egg-info/top_level.txt