Metadata-Version: 1.1
Name: subseek
Version: 2.8
Summary: Search subtitles for all your movies and series with a single command line script
Home-page: https://github.com/fedemotta/subseek
Author: Federico Nicolas Motta
Author-email: fedemotta@gmail.com
License: MIT
Download-URL: https://github.com/fedemotta/subseek/tarball/v2.8
Keywords: subtitles movies series batch script
Platform: UNKNOWN
Classifier: Development Status :: 5 - Production/Stable
Classifier: Intended Audience :: Developers
Classifier: Topic :: Utilities
Classifier: License :: OSI Approved :: MIT License
Classifier: Programming Language :: Python :: 2
Classifier: Programming Language :: Python :: 2.6
Classifier: Programming Language :: Python :: 2.7
Classifier: Programming Language :: Python :: 3.0
